swarmauri_middleware_llamaguard/LlamaGuardMiddleware.py
swarmauri_middleware_llamaguard/__init__.py
swarmauri_middleware_llamaguard-0.7.0.dev4.dist-info/LICENSE
swarmauri_middleware_llamaguard-0.7.0.dev4.dist-info/METADATA
swarmauri_middleware_llamaguard-0.7.0.dev4.dist-info/WHEEL
swarmauri_middleware_llamaguard-0.7.0.dev4.dist-info/entry_points.txt
swarmauri_middleware_llamaguard-0.7.0.dev4.dist-info/RECORD
