Metadata-Version: 2.3
Name: swarmauri_middleware_llamaguard
Version: 0.7.0.dev4
Summary: Middleware for inspecting and filtering unsafe content using LlamaGuard
License: Apache-2.0
Author: Jacob Stewart
Author-email: jacob@swarmauri.com
Requires-Python: >=3.10,<3.13
Classifier: License :: OSI Approved :: Apache Software License
Classifier: Natural Language :: English
Classifier: Programming Language :: Python :: 3.10
Classifier: Programming Language :: Python :: 3.11
Classifier: Programming Language :: Python :: 3.12
Classifier: Programming Language :: Python :: 3.13
Classifier: Development Status :: 3 - Alpha
Requires-Dist: fastapi
Requires-Dist: python-dotenv (>=1.0.0)
Requires-Dist: swarmauri_base
Requires-Dist: swarmauri_core
Requires-Dist: swarmauri_standard
